pineflow/readers/watson_discovery/__init__.py
pineflow/readers/watson_discovery/base.py
pineflow_readers_watson_discovery-0.7.1.dist-info/METADATA
pineflow_readers_watson_discovery-0.7.1.dist-info/WHEEL
pineflow_readers_watson_discovery-0.7.1.dist-info/RECORD
